cea_external_tools/__init__.py
cea_external_tools/bin/ds_illum.exe
cea_external_tools/bin/epw2wea.exe
cea_external_tools/bin/gen_dc.exe
cea_external_tools/bin/mesh-generation.exe
cea_external_tools/bin/oconv.exe
cea_external_tools/bin/radfiles2daysim.exe
cea_external_tools/bin/radiation.exe
cea_external_tools/bin/rtrace_dc.exe
cea_external_tools-0.2.1.dist-info/METADATA
cea_external_tools-0.2.1.dist-info/WHEEL
cea_external_tools-0.2.1.dist-info/RECORD
