Metadata-Version: 2.2
Name: cea-external-tools
Version: 0.2.1
Summary: External tools for City Energy Analyst, mainly containing C++ components e.g. DAYSIM and CRAX
Author-Email: Reynold Mok <reynold.mok@arch.ethz.ch>
Project-URL: Homepage, https://cityenergyanalyst.com
Project-URL: Bug Reports, https://github.com/architecture-building-systems/CityEnergyAnalyst/issues
Project-URL: Source, https://github.com/architecture-building-systems/CityEnergyAnalyst
Requires-Python: <3.13,>=3.8
